rrpproxypy/__init__.py
rrpproxypy/args.py
rrpproxypy/client.py
rrpproxypy/exceptions.py
rrpproxypy-0.1.2.dist-info/LICENSE
rrpproxypy-0.1.2.dist-info/METADATA
rrpproxypy-0.1.2.dist-info/WHEEL
rrpproxypy-0.1.2.dist-info/top_level.txt
rrpproxypy-0.1.2.dist-info/RECORD
