Metadata-Version: 2.1
Name: rrpproxypy
Version: 0.1.2
Summary: Python interface to the RRPproxy API.
Home-page: https://github.com/Smoose-bv/rrpproxypy
Author: Smoose BV
License: GPL-3
Keywords: rrpproxy rrp api library
Platform: UNKNOWN
Classifier: Programming Language :: Python :: 3
Classifier: License :: OSI Approved :: GNU General Public License v3 (GPLv3)
Classifier: Operating System :: OS Independent
Requires-Dist: requests (>=2.21.0)
